{
	"files": [

	],
	"folders": {
		"Characters": {
			"files": [
				"character-1685486643.json"
			],
			"folders": {

			},
			"metadata": {
				"color": null,
				"folded": false
			}
		},
		"Definitions": {
			"files": [
				"1685495754-648"
			],
			"folders": {

			},
			"metadata": {
				"color": null,
				"folded": false
			}
		},
		"Themes": {
			"files": [
				"default-theme.cfg",
				"theme-1685495375.cfg"
			],
			"folders": {

			},
			"metadata": {
				"color": null,
				"folded": false
			}
		},
		"Timelines": {
			"files": [
				"timeline-1685492934.json",
				"timeline-1685560974.json",
				"timeline-1685494867.json"
			],
			"folders": {

			},
			"metadata": {
				"color": null,
				"folded": false
			}
		}
	}
}
